{
  "reg": [
    {
      "FirstName": "Esegboriah",
      "LastName": "Immarayi",
      "id": "8_Hzxp",
      "Bio": "Engrg Manager at Guiness, Owner of several multinational companies in Africa",
      " Phone": "09027384927",
      "Worth": "$20,000,000",
      "Photo": "Ese"
    },
    {
      "FirstName": "Courage",
      "LastName": "Osemwengie",
      "id": "8hsH5",
      "Bio": "Lead software developer at microsoft and the Honorable CEO Tech & Devs",
      "Phone": "08062537182",
      "Worth": "$18,000,000",
      "Photo": "Ab"
    },
    {
      "FirstName": "Abraham",
      "LastName": "Momoh",
      "id": "JDhs_3",
      "Bio": "Mayor of Banana Island and execute officer of PalmsDays, started business at very early age in Edo",
      "Phone": "0980263782831",
      "Worth": "$50,000,000",
      "Photo": "Blessed"
    },
    {
      "FirstName": "Osayuki",
      "LastName": "Omoreghae",
      "id": "Ss3u7",
      "Bio": "A business mogul with lots of branches scattered all over Africa Mr Diator is the CEO iSELL26.com",
      "Phone": "08163826187",
      "Worth": "$100,000,000",
      "Photo": "Yuki"
    },
    {
      "FirstName": "Orobosa",
      "LastName": "Oriakhi",
      "id": "ahJS6",
      "Bio": "Regional Manager at KFC United States",
      "Phone": "08163826187",
      "Worth": "$40,000,000",
      "Photo": "Blessed"
    }
  ]
}